README.md
pyproject.toml
setup.cfg
setup.py
leo_station_keeping/__init__.py
leo_station_keeping/api_client.py
leo_station_keeping/api_response.py
leo_station_keeping/configuration.py
leo_station_keeping/exceptions.py
leo_station_keeping/py.typed
leo_station_keeping/rest.py
leo_station_keeping.egg-info/PKG-INFO
leo_station_keeping.egg-info/SOURCES.txt
leo_station_keeping.egg-info/dependency_links.txt
leo_station_keeping.egg-info/requires.txt
leo_station_keeping.egg-info/top_level.txt
leo_station_keeping/api/__init__.py
leo_station_keeping/api/default_api.py
leo_station_keeping/models/__init__.py
leo_station_keeping/models/advanced_orbit_parameters.py
leo_station_keeping/models/along_track_tolerance.py
leo_station_keeping/models/analytical_leo_station_keeping_request.py
leo_station_keeping/models/analytical_leo_station_keeping_request_drag_perturbation.py
leo_station_keeping/models/analytical_leo_station_keeping_response.py
leo_station_keeping/models/atmospheric_model.py
leo_station_keeping/models/axis.py
leo_station_keeping/models/battery.py
leo_station_keeping/models/body_solar_array.py
leo_station_keeping/models/box_spacecraft_geometry.py
leo_station_keeping/models/box_spacecraft_geometry_all_of_thruster_axis.py
leo_station_keeping/models/cartesian_ephemerides.py
leo_station_keeping/models/circular_altitude_orbit_parameters.py
leo_station_keeping/models/circular_ground_track_repeated_orbit_parameters.py
leo_station_keeping/models/custom_earth_potential_configuration.py
leo_station_keeping/models/custom_maneuvering_strategy.py
leo_station_keeping/models/custom_thrust_arcs_position.py
leo_station_keeping/models/deployable_fixed_solar_array.py
leo_station_keeping/models/deployable_rotating_solar_array.py
leo_station_keeping/models/drag_perturbation.py
leo_station_keeping/models/duty_cycle_thrust_arc_definition.py
leo_station_keeping/models/earth_potential_perturbation.py
leo_station_keeping/models/elliptical_ground_track_repeated_eccentricity_orbit_parameters.py
leo_station_keeping/models/elliptical_perigee_alt_apogee_alt_orbit_parameters.py
leo_station_keeping/models/elliptical_perigee_alt_eccentricity_orbit_parameters.py
